{
	"height": 12,
	"origin": {
		"x": 8,
		"y": 167
	},
	"null-character": 32,
	"overlays": {
		"scene": {
			"x": 0,
			"y": 0,
			"title": "Scene",
			"default": "oldman-standing",
			"options": {
				"ashura1": {
					"x": 0,
					"y": 16,
					"w": 256,
					"h": 160
				},
				"ashura2": {
					"x": 256,
					"y": 16,
					"w": 256,
					"h": 160
				},
				"oldman-collapsed": {
					"x": 0,
					"y": 176,
					"w": 256,
					"h": 160
				},
				"oldman-standing": {
					"x": 256,
					"y": 176,
					"w": 256,
					"h": 160
				},
				"sorceress1": {
					"x": 0,
					"y": 336,
					"w": 256,
					"h": 160
				},
				"sorceress2": {
					"x": 256,
					"y": 336,
					"w": 256,
					"h": 160
				},
				"sorceress3": {
					"x": 0,
					"y": 496,
					"w": 256,
					"h": 160
				}
			}
		}
	},
	"subfonts": {
		"cyan": {
			"height": 12,
			"origin": {
				"x": 8,
				"y": 167
			},
			"null-character": 32,
			"default": {
				"w": 8,
				"h": 8,
				"y": 8
			},

			"32": {
				"x": 0
			},
			"48": {
				"x": 8
			},
			"49": {
				"x": 16
			},
			"50": {
				"x": 24
			},
			"51": {
				"x": 32
			},
			"52": {
				"x": 40
			},
			"53": {
				"x": 48
			},
			"54": {
				"x": 56
			},
			"55": {
				"x": 64
			},
			"56": {
				"x": 72
			},
			"57": {
				"x": 80
			},
			"65": {
				"x": 88
			},
			"66": {
				"x": 96
			},
			"67": {
				"x": 104
			},
			"68": {
				"x": 112
			},
			"69": {
				"x": 120
			},
			"70": {
				"x": 128
			},
			"71": {
				"x": 136
			},
			"72": {
				"x": 144
			},
			"73": {
				"x": 152
			},
			"74": {
				"x": 160
			},
			"75": {
				"x": 168
			},
			"76": {
				"x": 176
			},
			"77": {
				"x": 184
			},
			"78": {
				"x": 192
			},
			"79": {
				"x": 200
			},
			"80": {
				"x": 208
			},
			"81": {
				"x": 216
			},
			"82": {
				"x": 224
			},
			"83": {
				"x": 232
			},
			"84": {
				"x": 240
			},
			"85": {
				"x": 248
			},
			"86": {
				"x": 256
			},
			"87": {
				"x": 264
			},
			"88": {
				"x": 272
			},
			"89": {
				"x": 280
			},
			"90": {
				"x": 288
			},
			"97": {
				"x": 296
			},
			"98": {
				"x": 304
			},
			"99": {
				"x": 312
			},
			"100": {
				"x": 320
			},
			"101": {
				"x": 328
			},
			"102": {
				"x": 336
			},
			"103": {
				"x": 344
			},
			"104": {
				"x": 352
			},
			"105": {
				"x": 360
			},
			"106": {
				"x": 368
			},
			"107": {
				"x": 376
			},
			"108": {
				"x": 384
			},
			"109": {
				"x": 392
			},
			"110": {
				"x": 400
			},
			"111": {
				"x": 408
			},
			"112": {
				"x": 416
			},
			"113": {
				"x": 424
			},
			"114": {
				"x": 432
			},
			"115": {
				"x": 440
			},
			"116": {
				"x": 448
			},
			"117": {
				"x": 456
			},
			"118": {
				"x": 464
			},
			"119": {
				"x": 472
			},
			"120": {
				"x": 480
			},
			"121": {
				"x": 488
			},
			"122": {
				"x": 496
			},
			"45": {
				"x": 504
			},
			"46": {
				"x": 512
			},
			"44": {
				"x": 520
			},
			"63": {
				"x": 528
			},
			"33": {
				"x": 536
			},
			"8229": {
				"x": 544
			},
			"39": {
				"x": 552
			},
			"9660": {
				"x": 560
			},
			"169": {
				"x": 568
			},
			"38": {
				"x": 576
			},
			"40": {
				"x": 584
			},
			"41": {
				"x": 592
			}
		}
	},

	"default": {
		"w": 8,
		"h": 8
	},
	"32": {
		"x": 0
	},
	"48": {
		"x": 8
	},
	"49": {
		"x": 16
	},
	"50": {
		"x": 24
	},
	"51": {
		"x": 32
	},
	"52": {
		"x": 40
	},
	"53": {
		"x": 48
	},
	"54": {
		"x": 56
	},
	"55": {
		"x": 64
	},
	"56": {
		"x": 72
	},
	"57": {
		"x": 80
	},
	"65": {
		"x": 88
	},
	"66": {
		"x": 96
	},
	"67": {
		"x": 104
	},
	"68": {
		"x": 112
	},
	"69": {
		"x": 120
	},
	"70": {
		"x": 128
	},
	"71": {
		"x": 136
	},
	"72": {
		"x": 144
	},
	"73": {
		"x": 152
	},
	"74": {
		"x": 160
	},
	"75": {
		"x": 168
	},
	"76": {
		"x": 176
	},
	"77": {
		"x": 184
	},
	"78": {
		"x": 192
	},
	"79": {
		"x": 200
	},
	"80": {
		"x": 208
	},
	"81": {
		"x": 216
	},
	"82": {
		"x": 224
	},
	"83": {
		"x": 232
	},
	"84": {
		"x": 240
	},
	"85": {
		"x": 248
	},
	"86": {
		"x": 256
	},
	"87": {
		"x": 264
	},
	"88": {
		"x": 272
	},
	"89": {
		"x": 280
	},
	"90": {
		"x": 288
	},
	"97": {
		"x": 296
	},
	"98": {
		"x": 304
	},
	"99": {
		"x": 312
	},
	"100": {
		"x": 320
	},
	"101": {
		"x": 328
	},
	"102": {
		"x": 336
	},
	"103": {
		"x": 344
	},
	"104": {
		"x": 352
	},
	"105": {
		"x": 360
	},
	"106": {
		"x": 368
	},
	"107": {
		"x": 376
	},
	"108": {
		"x": 384
	},
	"109": {
		"x": 392
	},
	"110": {
		"x": 400
	},
	"111": {
		"x": 408
	},
	"112": {
		"x": 416
	},
	"113": {
		"x": 424
	},
	"114": {
		"x": 432
	},
	"115": {
		"x": 440
	},
	"116": {
		"x": 448
	},
	"117": {
		"x": 456
	},
	"118": {
		"x": 464
	},
	"119": {
		"x": 472
	},
	"120": {
		"x": 480
	},
	"121": {
		"x": 488
	},
	"122": {
		"x": 496
	},
	"45": {
		"x": 504
	},
	"46": {
		"x": 512
	},
	"44": {
		"x": 520
	},
	"63": {
		"x": 528
	},
	"33": {
		"x": 536
	},
	"8229": {
		"x": 544
	},
	"39": {
		"x": 552
	},
	"9660": {
		"x": 560
	},
	"169": {
		"x": 568
	},
	"38": {
		"x": 576
	},
	"40": {
		"x": 584
	},
	"41": {
		"x": 592
	}
}