{
	"height": 12,
	"origin": {
		"y": 177,
		"x": 128
	},
	"default": {
		"unadvance": 1
	},
	"justify": "all-center",
	"overlays": {
		"portrait": {
			"x": 80,
			"y": 24,
			"title": "Portrait",
			"default": "yumi",
			"options": {
				"boss": {
					"x": 0,
					"y": 11,
					"w": 96,
					"h": 96
				},
				"dad": {
					"x": 96,
					"y": 11,
					"w": 96,
					"h": 96
				},
				"yumi": {
					"x": 192,
					"y": 11,
					"w": 96,
					"h": 96
				}
			}
		}
	},
	"32": {
		"x": 818,
		"w": 5,
		"h": 10
	},
	"33": {
		"x": 608,
		"w": 6,
		"h": 10
	},
	"34": {
		"x": 655,
		"w": 7,
		"h": 10
	},
	"35": {
		"x": 645,
		"w": 9,
		"h": 10
	},
	"36": {
		"x": 793,
		"w": 8,
		"h": 10
	},
	"37": {
		"x": 783,
		"w": 9,
		"h": 10
	},
	"38": {
		"x": 669,
		"w": 9,
		"h": 10
	},
	"39": {
		"x": 663,
		"w": 5,
		"h": 10
	},
	"40": {
		"x": 679,
		"w": 5,
		"h": 10
	},
	"41": {
		"x": 685,
		"w": 5,
		"h": 10
	},
	"43": {
		"x": 764,
		"w": 8,
		"h": 10
	},
	"44": {
		"x": 584,
		"w": 4,
		"h": 10
	},
	"45": {
		"x": 615,
		"w": 9,
		"h": 10
	},
	"46": {
		"x": 579,
		"w": 4,
		"h": 10
	},
	"47": {
		"x": 738,
		"w": 7,
		"h": 10
	},
	"48": {
		"x": 479,
		"w": 9,
		"h": 10
	},
	"49": {
		"x": 489,
		"w": 9,
		"h": 10
	},
	"50": {
		"x": 499,
		"w": 9,
		"h": 10
	},
	"51": {
		"x": 509,
		"w": 9,
		"h": 10
	},
	"52": {
		"x": 519,
		"w": 9,
		"h": 10
	},
	"53": {
		"x": 529,
		"w": 9,
		"h": 10
	},
	"54": {
		"x": 539,
		"w": 9,
		"h": 10
	},
	"55": {
		"x": 549,
		"w": 9,
		"h": 10
	},
	"56": {
		"x": 559,
		"w": 9,
		"h": 10
	},
	"57": {
		"x": 569,
		"w": 9,
		"h": 10
	},
	"58": {
		"x": 594,
		"w": 4,
		"h": 10
	},
	"59": {
		"x": 589,
		"w": 4,
		"h": 10
	},
	"60": {
		"x": 802,
		"w": 7,
		"h": 10
	},
	"61": {
		"x": 773,
		"w": 9,
		"h": 10
	},
	"62": {
		"x": 810,
		"w": 7,
		"h": 10
	},
	"63": {
		"x": 599,
		"w": 8,
		"h": 10
	},
	"64": {
		"x": 754,
		"w": 9,
		"h": 10
	},
	"65": {
		"x": 1,
		"w": 9,
		"h": 10
	},
	"66": {
		"x": 11,
		"w": 9,
		"h": 10
	},
	"67": {
		"x": 21,
		"w": 9,
		"h": 10
	},
	"68": {
		"x": 31,
		"w": 9,
		"h": 10
	},
	"69": {
		"x": 41,
		"w": 9,
		"h": 10
	},
	"70": {
		"x": 51,
		"w": 9,
		"h": 10
	},
	"71": {
		"x": 61,
		"w": 9,
		"h": 10
	},
	"72": {
		"x": 71,
		"w": 9,
		"h": 10
	},
	"73": {
		"x": 81,
		"w": 8,
		"h": 10
	},
	"74": {
		"x": 90,
		"w": 9,
		"h": 10
	},
	"75": {
		"x": 100,
		"w": 9,
		"h": 10
	},
	"76": {
		"x": 110,
		"w": 9,
		"h": 10
	},
	"77": {
		"x": 120,
		"w": 9,
		"h": 10
	},
	"78": {
		"x": 130,
		"w": 9,
		"h": 10
	},
	"79": {
		"x": 140,
		"w": 9,
		"h": 10
	},
	"80": {
		"x": 150,
		"w": 9,
		"h": 10
	},
	"81": {
		"x": 160,
		"w": 9,
		"h": 10
	},
	"82": {
		"x": 170,
		"w": 9,
		"h": 10
	},
	"83": {
		"x": 180,
		"w": 9,
		"h": 10
	},
	"84": {
		"x": 190,
		"w": 8,
		"h": 10
	},
	"85": {
		"x": 199,
		"w": 9,
		"h": 10
	},
	"86": {
		"x": 209,
		"w": 9,
		"h": 10
	},
	"87": {
		"x": 219,
		"w": 9,
		"h": 10
	},
	"88": {
		"x": 229,
		"w": 9,
		"h": 10
	},
	"89": {
		"x": 239,
		"w": 8,
		"h": 10
	},
	"90": {
		"x": 248,
		"w": 9,
		"h": 10
	},
	"91": {
		"x": 691,
		"w": 5,
		"h": 10
	},
	"92": {
		"x": 746,
		"w": 7,
		"h": 10
	},
	"93": {
		"x": 697,
		"w": 5,
		"h": 10
	},
	"94": {
		"x": 717,
		"w": 9,
		"h": 10
	},
	"95": {
		"x": 625,
		"w": 9,
		"h": 10
	},
	"96": {
		"x": 732,
		"w": 5,
		"h": 10
	},
	"97": {
		"x": 258,
		"w": 8,
		"h": 10
	},
	"98": {
		"x": 267,
		"w": 8,
		"h": 10
	},
	"99": {
		"x": 276,
		"w": 8,
		"h": 10
	},
	"100": {
		"x": 285,
		"w": 8,
		"h": 10
	},
	"101": {
		"x": 294,
		"w": 8,
		"h": 10
	},
	"102": {
		"x": 303,
		"w": 7,
		"h": 10
	},
	"103": {
		"x": 311,
		"w": 8,
		"h": 10
	},
	"104": {
		"x": 320,
		"w": 8,
		"h": 10
	},
	"105": {
		"x": 329,
		"w": 4,
		"h": 10
	},
	"106": {
		"x": 334,
		"w": 5,
		"h": 10
	},
	"107": {
		"x": 340,
		"w": 8,
		"h": 10
	},
	"108": {
		"x": 349,
		"w": 4,
		"h": 10
	},
	"109": {
		"x": 354,
		"w": 9,
		"h": 10
	},
	"110": {
		"x": 364,
		"w": 8,
		"h": 10
	},
	"111": {
		"x": 373,
		"w": 8,
		"h": 10
	},
	"112": {
		"x": 382,
		"w": 8,
		"h": 10
	},
	"113": {
		"x": 391,
		"w": 8,
		"h": 10
	},
	"114": {
		"x": 400,
		"w": 7,
		"h": 10
	},
	"115": {
		"x": 408,
		"w": 8,
		"h": 10
	},
	"116": {
		"x": 417,
		"w": 6,
		"h": 10
	},
	"117": {
		"x": 424,
		"w": 8,
		"h": 10
	},
	"118": {
		"x": 433,
		"w": 7,
		"h": 10
	},
	"119": {
		"x": 441,
		"w": 9,
		"h": 10
	},
	"120": {
		"x": 451,
		"w": 9,
		"h": 10
	},
	"121": {
		"x": 461,
		"w": 8,
		"h": 10
	},
	"122": {
		"x": 470,
		"w": 8,
		"h": 10
	},
	"123": {
		"x": 703,
		"w": 6,
		"h": 10
	},
	"124": {
		"x": 727,
		"w": 4,
		"h": 10
	},
	"125": {
		"x": 710,
		"w": 6,
		"h": 10
	},
	"126": {
		"x": 635,
		"w": 9,
		"h": 10
	},
	"11013": {
		"x": 824,
		"w": 13,
		"h": 10
	},
	"10145": {
		"x": 838,
		"w": 13,
		"h": 10
	},
	"11015": {
		"x": 852,
		"w": 13,
		"h": 10
	},
	"11014": {
		"x": 866,
		"w": 13,
		"h": 10
	},
	"127305": {
		"x": 880,
		"w": 13,
		"h": 10
	},
	"127303": {
		"x": 894,
		"w": 13,
		"h": 10
	},
	"127289": {
		"x": 908,
		"w": 13,
		"h": 10
	},
	"127291": {
		"x": 922,
		"w": 13,
		"h": 10
	},
	"127290": {
		"x": 936,
		"w": 13,
		"h": 10
	},
	"127288": {
		"x": 950,
		"w": 13,
		"h": 10
	},
	"9166": {
		"x": 964,
		"w": 41,
		"h": 10
	}
}